carinanet/__init__.py
carinanet/api.py
carinanet/cli.py
carinanet/utils.py
carinanet/core_utils/AnnotationLoader.py
carinanet/core_utils/__init__.py
carinanet/core_utils/coco_utils.py
carinanet/core_utils/constants.py
carinanet/core_utils/model_helpers.py
carinanet/models/__init__.py
carinanet/models/carinanet_model.py
carinanet/models/ettmodel.py
carinanet/models/retinanet/__init__.py
carinanet/models/retinanet/anchors.py
carinanet/models/retinanet/dataloader.py
carinanet/models/retinanet/losses.py
carinanet/models/retinanet/model.py
carinanet/models/retinanet/utils.py
factchexcker_carinanet-1.1.0.dist-info/licenses/LICENSE
factchexcker_carinanet-1.1.0.dist-info/METADATA
factchexcker_carinanet-1.1.0.dist-info/WHEEL
factchexcker_carinanet-1.1.0.dist-info/entry_points.txt
factchexcker_carinanet-1.1.0.dist-info/top_level.txt
factchexcker_carinanet-1.1.0.dist-info/RECORD
