Metadata-Version: 2.4
Name: factchexcker-carinanet
Version: 1.1.0
Summary: Automatic detection of carina and ETT in chest X-rays using deep learning
Home-page: https://github.com/rajpurkarlab/carinanet
Author: Xiaoman Zhang
Author-email: Xiaoman Zhang <xiaomanzhang.zxm@gmail.com>
Maintainer-email: Xiaoman Zhang <xiaomanzhang.zxm@gmail.com>
Project-URL: Homepage, https://github.com/rajpurkarlab/carinanet
Project-URL: Repository, https://github.com/rajpurkarlab/carinanet
Project-URL: Issues, https://github.com/rajpurkarlab/carinanet/issues
Project-URL: Documentation, https://github.com/rajpurkarlab/carinanet#readme
Keywords: medical,ai,chest-xray,carina,ett,deep-learning,computer-vision,medical-imaging
Classifier: Development Status :: 4 - Beta
Classifier: Intended Audience :: Science/Research
Classifier: Intended Audience :: Healthcare Industry
Classifier: Operating System :: OS Independent
Classifier: Programming Language :: Python :: 3
Classifier: Programming Language :: Python :: 3.8
Classifier: Programming Language :: Python :: 3.9
Classifier: Programming Language :: Python :: 3.10
Classifier: Programming Language :: Python :: 3.11
Classifier: Topic :: Scientific/Engineering :: Artificial Intelligence
Classifier: Topic :: Scientific/Engineering :: Medical Science Apps.
Classifier: Topic :: Scientific/Engineering :: Image Processing
Requires-Python: >=3.8
License-File: LICENSE
Requires-Dist: torch>=1.9.0
Requires-Dist: torchvision>=0.10.0
Requires-Dist: Pillow>=8.0.0
Requires-Dist: numpy>=1.19.0
Requires-Dist: requests>=2.25.0
Requires-Dist: tqdm>=4.60.0
Requires-Dist: kwcoco>=0.2.0
Requires-Dist: pandas>=1.3.0
Requires-Dist: scikit-image>=0.18.0
Requires-Dist: pycocotools>=2.0.0
Requires-Dist: huggingface_hub>=0.15.0
Provides-Extra: dev
Requires-Dist: wandb; extra == "dev"
Requires-Dist: pytest; extra == "dev"
Requires-Dist: black; extra == "dev"
Requires-Dist: isort; extra == "dev"
Requires-Dist: mypy; extra == "dev"
Dynamic: author
Dynamic: home-page
Dynamic: license-file
Dynamic: requires-python
